.travis.yml
CHANGES.rst
MANIFEST.in
README.rst
bootstrap.py
buildout.cfg
setup.py
tox.ini
src/zc/__init__.py
src/zc.zlibstorage.egg-info/PKG-INFO
src/zc.zlibstorage.egg-info/SOURCES.txt
src/zc.zlibstorage.egg-info/dependency_links.txt
src/zc.zlibstorage.egg-info/entry_points.txt
src/zc.zlibstorage.egg-info/namespace_packages.txt
src/zc.zlibstorage.egg-info/not-zip-safe
src/zc.zlibstorage.egg-info/requires.txt
src/zc.zlibstorage.egg-info/top_level.txt
src/zc/zlibstorage/README.txt
src/zc/zlibstorage/__init__.py
src/zc/zlibstorage/component.xml
src/zc/zlibstorage/tests.py